setup.py
intraday/__init__.py
intraday.egg-info/PKG-INFO
intraday.egg-info/SOURCES.txt
intraday.egg-info/dependency_links.txt
intraday.egg-info/top_level.txt