Metadata-Version: 1.1
Name: intraday
Version: 1.0.0
Summary: This module is used to scarp earning information from both yahoo and nasdaq
Home-page: https://github.com/ShallweXiaowei/intraday
Author: Xiaowei Yan
Author-email: shufeyxw@gmail.com
License: MIT
Download-URL: https://github.com/ShallweXiaowei/intraday/archive/1.0.0.tar.gz
Platform: UNKNOWN
